{
  "Üç Silahşörler||2011": {
    "extinf": "#EXTINF:-1 tvg-name=\"Üç Silahşörler\" tvg-logo=\"https://image.tmdb.org/t/p/w500/ss2IjJib51ZPYqZ5Yzb4ZTFEo1D.jpg\" group-title=\"VOD\" title=\"Üç Silahşörler\" desc=\"Fransa Kralı’nın sadık silahşörleri Atos, Porthos ve Aremis, krala düzenlenecek bir komplonun duyumunu aldıklarında, yanlarına genç D’Artagnan’ı da alarak tehlikeli bir maceraya atılırlar. Fakat bu zorlu yolda ilerledikçe, dört kahraman sadece Fransa Kralı’nın değil, tüm Avrupa’nın tehlikede olduğunu anlarlar. Kardinal Richelieu, yardımcıları ile birlikte krallık tacını ele geçirip, ülkenin tek hâkimi olmak için şeytanca bir plan kurmuştur. Ona bu planda destek olan ajan Milady de Winter da silahşörlerden Athos’u kendine aşık etmeyi kolayca başarmıştır...\" rating=\"5.797\" actors=\"Logan Lerman, Milla Jovovich, Matthew Macfadyen, Ray Stevenson, Luke Evans\" director=\"Paul W. S. Anderson\"",
    "title": "Üç Silahşörler",
    "poster": "https://image.tmdb.org/t/p/w500/ss2IjJib51ZPYqZ5Yzb4ZTFEo1D.jpg",
    "overview": "Fransa Kralı’nın sadık silahşörleri Atos, Porthos ve Aremis, krala düzenlenecek bir komplonun duyumunu aldıklarında, yanlarına genç D’Artagnan’ı da alarak tehlikeli bir maceraya atılırlar. Fakat bu zorlu yolda ilerledikçe, dört kahraman sadece Fransa Kralı’nın değil, tüm Avrupa’nın tehlikede olduğunu anlarlar. Kardinal Richelieu, yardımcıları ile birlikte krallık tacını ele geçirip, ülkenin tek hâkimi olmak için şeytanca bir plan kurmuştur. Ona bu planda destek olan ajan Milady de Winter da silahşörlerden Athos’u kendine aşık etmeyi kolayca başarmıştır...",
    "rating": "5.797",
    "actors": "Logan Lerman, Milla Jovovich, Matthew Macfadyen, Ray Stevenson, Luke Evans",
    "director": "Paul W. S. Anderson",
    "unsure": false
  },
  "Ucubeler Sirki - Vampirin Çırağı||2009": {
    "extinf": "#EXTINF:-1 tvg-name=\"Ucubeler Sirki: Vampirin Çırağı\" tvg-logo=\"https://image.tmdb.org/t/p/w500/l0mKBRXmuvUMI5PIcCFUWy7eWf8.jpg\" group-title=\"VOD\" title=\"Ucubeler Sirki: Vampirin Çırağı\" desc=\"Birbiriyle savaş halinde olan 2 vampir grubu arasındaki 200 yıllık ateşkesi farkında olmadan bozan bir gencin korkunç hikayesi anlatılıyor.Gecenin grotesk canlıları ve yanlış anlaşılan ucubelerin fantastik hayatı içine çekilen bir genç, sıkıcı bir hayatın güvenli ortamından uzaklaşacak ve kâbuslardan fırlamış gibi görünen bir yerde kaderini yaşayacak.\" rating=\"5.9\" actors=\"Chris Massoglia, John C. Reilly, Josh Hutcherson, Patrick Fugit, Salma Hayek Pinault\" director=\"Paul Weitz\"",
    "title": "Ucubeler Sirki: Vampirin Çırağı",
    "poster": "https://image.tmdb.org/t/p/w500/l0mKBRXmuvUMI5PIcCFUWy7eWf8.jpg",
    "overview": "Birbiriyle savaş halinde olan 2 vampir grubu arasındaki 200 yıllık ateşkesi farkında olmadan bozan bir gencin korkunç hikayesi anlatılıyor.Gecenin grotesk canlıları ve yanlış anlaşılan ucubelerin fantastik hayatı içine çekilen bir genç, sıkıcı bir hayatın güvenli ortamından uzaklaşacak ve kâbuslardan fırlamış gibi görünen bir yerde kaderini yaşayacak.",
    "rating": "5.9",
    "actors": "Chris Massoglia, John C. Reilly, Josh Hutcherson, Patrick Fugit, Salma Hayek Pinault",
    "director": "Paul Weitz",
    "unsure": false
  },
  "Umut Kırıntıları||2014": {
    "extinf": "#EXTINF:-1 tvg-name=\"Umut Kırıntıları\" tvg-logo=\"https://image.tmdb.org/t/p/w500/fxUmT00PW2W6RDjmS8tbjWXDDj3.jpg\" group-title=\"VOD\" title=\"Umut Kırıntıları\" desc=\"Fakir bir ailenin çocuğu olan 14 yaşındaki Rafael ve 2 arkadaşı sıradan birgünde çöpleri karıştırdıkları sırada başlarını son derece belaya sokacak bir cüzdan bulacaktırlar, bu cüzdan Rafael ve arkadaşlarının hayatını biranda alt üst ederken çevreleride onları öldürmek isteyen polisler ile dolacaktır.\" rating=\"7.1\" actors=\"Rickson Tevez, Eduardo Luís, Gabriel Weinstein, Wagner Moura, Selton Mello\" director=\"Stephen Daldry\"",
    "title": "Umut Kırıntıları",
    "poster": "https://image.tmdb.org/t/p/w500/fxUmT00PW2W6RDjmS8tbjWXDDj3.jpg",
    "overview": "Fakir bir ailenin çocuğu olan 14 yaşındaki Rafael ve 2 arkadaşı sıradan birgünde çöpleri karıştırdıkları sırada başlarını son derece belaya sokacak bir cüzdan bulacaktırlar, bu cüzdan Rafael ve arkadaşlarının hayatını biranda alt üst ederken çevreleride onları öldürmek isteyen polisler ile dolacaktır.",
    "rating": "7.1",
    "actors": "Rickson Tevez, Eduardo Luís, Gabriel Weinstein, Wagner Moura, Selton Mello",
    "director": "Stephen Daldry",
    "unsure": false
  },
  "Upon The Magic Roads||2021": {
    "extinf": "#EXTINF:-1 tvg-name=\"Sihirli Yollarda\" tvg-logo=\"https://image.tmdb.org/t/p/w500/6sOzqhtSIZ2qu4mPQtdK1nS4JUJ.jpg\" group-title=\"VOD\" title=\"Sihirli Yollarda\" desc=\"Bir köylü ve küçük atı bir dizi maceraya atılır. Ateş kuşunu yakalayacaklar, bir balinayı serbest bırakacaklar ve gerçek aşkı bulacaklardır.\" rating=\"6.81\" actors=\"Антон Шагин, Павел Деревянко, Михаил Ефремов, Паулина Андреева, Ян Цапник\" director=\"Олег Погодин\" __UNSURE__",
    "title": "Sihirli Yollarda",
    "poster": "https://image.tmdb.org/t/p/w500/6sOzqhtSIZ2qu4mPQtdK1nS4JUJ.jpg",
    "overview": "Bir köylü ve küçük atı bir dizi maceraya atılır. Ateş kuşunu yakalayacaklar, bir balinayı serbest bırakacaklar ve gerçek aşkı bulacaklardır.",
    "rating": "6.81",
    "actors": "Антон Шагин, Павел Деревянко, Михаил Ефремов, Паулина Андреева, Ян Цапник",
    "director": "Олег Погодин",
    "unsure": true
  },
  "Uyumsuz - Yandaş 1||2016": {
    "extinf": "#EXTINF:-1 tvg-name=\"Yandaş\" tvg-logo=\"https://image.tmdb.org/t/p/w500/4VDbNUCxGGyYFt9BgHgdzprFZry.jpg\" group-title=\"VOD\" title=\"Yandaş\" desc=\"Uyumsuz’da sistemi alt üst eden bilgileri ortaya çıkardıktan sonra, Tris ve Dört’ün, Şikago’yu çevreleyen duvarların dışına kaçması gerekmekte, hayatlarında ilk defa bildikleri tek şehri ve sevdiklerini bırakmak zorundadırlar. Tris ve Dört’ün, Şikago duvarlarının arkasında devam etmekte olan ve bütün insanlığı tehdit eden savaşta kimden yana olacaklarına hızlı bir şekilde karar vermesi gerekecek ve Tris hayatta kalabilmek için cesaret, sadakat, fedakarlık ve aşk arasında imkansız bir seçim yapmaya mecbur bırakılacak.\" rating=\"6.106\" actors=\"Shailene Woodley, Theo James, Miles Teller, Zoë Kravitz, Naomi Watts\" director=\"Robert Schwentke\"",
    "title": "Yandaş",
    "poster": "https://image.tmdb.org/t/p/w500/4VDbNUCxGGyYFt9BgHgdzprFZry.jpg",
    "overview": "Uyumsuz’da sistemi alt üst eden bilgileri ortaya çıkardıktan sonra, Tris ve Dört’ün, Şikago’yu çevreleyen duvarların dışına kaçması gerekmekte, hayatlarında ilk defa bildikleri tek şehri ve sevdiklerini bırakmak zorundadırlar. Tris ve Dört’ün, Şikago duvarlarının arkasında devam etmekte olan ve bütün insanlığı tehdit eden savaşta kimden yana olacaklarına hızlı bir şekilde karar vermesi gerekecek ve Tris hayatta kalabilmek için cesaret, sadakat, fedakarlık ve aşk arasında imkansız bir seçim yapmaya mecbur bırakılacak.",
    "rating": "6.106",
    "actors": "Shailene Woodley, Theo James, Miles Teller, Zoë Kravitz, Naomi Watts",
    "director": "Robert Schwentke",
    "unsure": false
  },
  "Uzak Ufuklar||1992": {
    "extinf": "#EXTINF:-1 tvg-name=\"Uzak Ufuklar\" tvg-logo=\"https://image.tmdb.org/t/p/w500/ijACAC21KNkTAbZLMePgT2UK37q.jpg\" group-title=\"VOD\" title=\"Uzak Ufuklar\" desc=\"Joseph, babasının ölümünün ardından bu olayın peşini bırakmasa da başı, beladan kurtulmaz. En sonunda Stephen Chase isimli üstüyle tartışır ve sonunda ülkeyi terk etmeyi aklına koyar. Bu yolculukta ona eşlik edecek kişi ise Chase'in kendisinden nefret eden kızı Shannon olur. Shannon, Joseph'e yardımcı olur ve birlikte Amerika'ya kaçarlar. Amerika'ya vardıklarında Oklahoma'daki arazi satışlarında bir yer satın alma hayalleri kurarlar ve bunu gerçekleştirmek için büyük bir azimle çalışmaya başlarlar. Zorlu şartlar altında hayallerine yaklaşan ikili hem Shannon'ın ailesine hem de olumsuz şartlara karşı savaşmak zorundadır.\" rating=\"6.776\" actors=\"Tom Cruise, Nicole Kidman, Thomas Gibson, Robert Prosky, Barbara Babcock\" director=\"Ron Howard\"",
    "title": "Uzak Ufuklar",
    "poster": "https://image.tmdb.org/t/p/w500/ijACAC21KNkTAbZLMePgT2UK37q.jpg",
    "overview": "Joseph, babasının ölümünün ardından bu olayın peşini bırakmasa da başı, beladan kurtulmaz. En sonunda Stephen Chase isimli üstüyle tartışır ve sonunda ülkeyi terk etmeyi aklına koyar. Bu yolculukta ona eşlik edecek kişi ise Chase'in kendisinden nefret eden kızı Shannon olur. Shannon, Joseph'e yardımcı olur ve birlikte Amerika'ya kaçarlar. Amerika'ya vardıklarında Oklahoma'daki arazi satışlarında bir yer satın alma hayalleri kurarlar ve bunu gerçekleştirmek için büyük bir azimle çalışmaya başlarlar. Zorlu şartlar altında hayallerine yaklaşan ikili hem Shannon'ın ailesine hem de olumsuz şartlara karşı savaşmak zorundadır.",
    "rating": "6.776",
    "actors": "Tom Cruise, Nicole Kidman, Thomas Gibson, Robert Prosky, Barbara Babcock",
    "director": "Ron Howard",
    "unsure": false
  },
  "Uzaylılar Vücudumu Çaldı||2020": {
    "extinf": "#EXTINF:-1 tvg-name=\"Uzaylılar Vücudumu Çaldı\" tvg-logo=\"https://image.tmdb.org/t/p/w500/8hORwWyXsNqX7eDZPSNN5iVTckF.jpg\" group-title=\"VOD\" title=\"Uzaylılar Vücudumu Çaldı\" rating=\"4.267\" actors=\"Jayden Greig, Lauren McNamara, Dan Payne, Alex Zahara, Sean Quan\" director=\"Sean McNamara\"",
    "title": "Uzaylılar Vücudumu Çaldı",
    "poster": "https://image.tmdb.org/t/p/w500/8hORwWyXsNqX7eDZPSNN5iVTckF.jpg",
    "overview": "",
    "rating": "4.267",
    "actors": "Jayden Greig, Lauren McNamara, Dan Payne, Alex Zahara, Sean Quan",
    "director": "Sean McNamara",
    "unsure": false
  },
  "Uzun Kuyruk Marsupilami||2012": {
    "extinf": "#EXTINF:-1 tvg-name=\"Uzun Kuyruk\" tvg-logo=\"https://image.tmdb.org/t/p/w500/7H2hk9IzYhRPU0iPMOzEwJkeUBn.jpg\" group-title=\"VOD\" title=\"Uzun Kuyruk\" desc=\"Muhabir Dan Geraldo (Alain Chabat) bir haber için Palombia'ya vardığında, kısa bir süre sonra inanılmaz bir keşif yapacağının henüz farkında değildir... Dan, becerikli yerli rehberi Pablito (Jamel Debbouze) ile muhteşem haberler yapmasını sağlayacak heyecan verici bir macera sırasında sürekli yeni sürprizlerle karşılaşır. En önemlisi ise; Efsanevi ve zararlı bir hayvan olan Marsupilami gerçektir!\" rating=\"5.3\" actors=\"Alain Chabat, Jamel Debbouze, Fred Testot, Lambert Wilson, Patrick Timsit\" director=\"Alain Chabat\"",
    "title": "Uzun Kuyruk",
    "poster": "https://image.tmdb.org/t/p/w500/7H2hk9IzYhRPU0iPMOzEwJkeUBn.jpg",
    "overview": "Muhabir Dan Geraldo (Alain Chabat) bir haber için Palombia'ya vardığında, kısa bir süre sonra inanılmaz bir keşif yapacağının henüz farkında değildir... Dan, becerikli yerli rehberi Pablito (Jamel Debbouze) ile muhteşem haberler yapmasını sağlayacak heyecan verici bir macera sırasında sürekli yeni sürprizlerle karşılaşır. En önemlisi ise; Efsanevi ve zararlı bir hayvan olan Marsupilami gerçektir!",
    "rating": "5.3",
    "actors": "Alain Chabat, Jamel Debbouze, Fred Testot, Lambert Wilson, Patrick Timsit",
    "director": "Alain Chabat",
    "unsure": false
  },
  "Vahşetin Çağrısı||1935": {
    "extinf": "#EXTINF:-1 tvg-name=\"Vahşetin Çağrısı\" tvg-logo=\"https://image.tmdb.org/t/p/w500/lvWCJvI8xVM7hbpaXtXXG4clKFm.jpg\" group-title=\"VOD\" title=\"Vahşetin Çağrısı\" desc=\"Bir kızak köpeği olan Buck, Kaliforniya'daki hayatından koparılarak kızak çekmesi için Alaska'ya götürülür. Bir anda mutlu yuvasından ayrılıp hayatı tepetaklak olan Buck, Alaska'nın zorlu yaşamına uyum sağlamaya çalışır. Posta dağıtım işinin çaylağı olan Buck, gün geçtike bu dünyaya alışır. Onun bu vahşi hayata alışma sürecinde yaşadıkları, Buck'un kendisini keşfetmesini sağlayacaktır.\" rating=\"7.534\" actors=\"Harrison Ford, Dan Stevens, Colin Woodell, Karen Gillan, Omar Sy\" director=\"Chris Sanders\"",
    "title": "Vahşetin Çağrısı",
    "poster": "https://image.tmdb.org/t/p/w500/lvWCJvI8xVM7hbpaXtXXG4clKFm.jpg",
    "overview": "Bir kızak köpeği olan Buck, Kaliforniya'daki hayatından koparılarak kızak çekmesi için Alaska'ya götürülür. Bir anda mutlu yuvasından ayrılıp hayatı tepetaklak olan Buck, Alaska'nın zorlu yaşamına uyum sağlamaya çalışır. Posta dağıtım işinin çaylağı olan Buck, gün geçtike bu dünyaya alışır. Onun bu vahşi hayata alışma sürecinde yaşadıkları, Buck'un kendisini keşfetmesini sağlayacaktır.",
    "rating": "7.534",
    "actors": "Harrison Ford, Dan Stevens, Colin Woodell, Karen Gillan, Omar Sy",
    "director": "Chris Sanders",
    "unsure": false
  },
  "Vahşetin Çağrısı||2020": {
    "extinf": "#EXTINF:-1 tvg-name=\"Vahşetin Çağrısı\" tvg-logo=\"https://image.tmdb.org/t/p/w500/lvWCJvI8xVM7hbpaXtXXG4clKFm.jpg\" group-title=\"VOD\" title=\"Vahşetin Çağrısı\" desc=\"Bir kızak köpeği olan Buck, Kaliforniya'daki hayatından koparılarak kızak çekmesi için Alaska'ya götürülür. Bir anda mutlu yuvasından ayrılıp hayatı tepetaklak olan Buck, Alaska'nın zorlu yaşamına uyum sağlamaya çalışır. Posta dağıtım işinin çaylağı olan Buck, gün geçtike bu dünyaya alışır. Onun bu vahşi hayata alışma sürecinde yaşadıkları, Buck'un kendisini keşfetmesini sağlayacaktır.\" rating=\"7.534\" actors=\"Harrison Ford, Dan Stevens, Colin Woodell, Karen Gillan, Omar Sy\" director=\"Chris Sanders\"",
    "title": "Vahşetin Çağrısı",
    "poster": "https://image.tmdb.org/t/p/w500/lvWCJvI8xVM7hbpaXtXXG4clKFm.jpg",
    "overview": "Bir kızak köpeği olan Buck, Kaliforniya'daki hayatından koparılarak kızak çekmesi için Alaska'ya götürülür. Bir anda mutlu yuvasından ayrılıp hayatı tepetaklak olan Buck, Alaska'nın zorlu yaşamına uyum sağlamaya çalışır. Posta dağıtım işinin çaylağı olan Buck, gün geçtike bu dünyaya alışır. Onun bu vahşi hayata alışma sürecinde yaşadıkları, Buck'un kendisini keşfetmesini sağlayacaktır.",
    "rating": "7.534",
    "actors": "Harrison Ford, Dan Stevens, Colin Woodell, Karen Gillan, Omar Sy",
    "director": "Chris Sanders",
    "unsure": false
  },
  "Vahşi Çocuklar 6||2016": null,
  "Vahşi Dostum||2018": {
    "extinf": "#EXTINF:-1 tvg-name=\"Vahşi Dostum\" tvg-logo=\"https://image.tmdb.org/t/p/w500/jT2eE40R4PWEJ7PGIV4xEeZSsFb.jpg\" group-title=\"VOD\" title=\"Vahşi Dostum\" desc=\"On yaşındaki Mia’nın Londra’da mutlu bir hayatı vardır. Fakat bir aslan çiftliğini işletmek için ailesi Güney Afrika’ya taşınmaya karar verir. Mia, başlarda bu karardan dolayı oldukça mutsuzdur. Fakat bembeyaz bir aslan olan Charlie doğduğunda Mia’nın hayatı güzelleşmeye başlar. Mia ve Charlie’nin arasında mükemmel bir bağ oluşmuştur. Her şey yolunda giderken babasının sakladığı sırrın ortaya çıkması ailenin hayatını alt üst eder. Öğrendiklerinden sonra Charlie’nin zarar görebileceğini düşünen Mia, Charlie ile birlikte kaçar. Charlie’nin yaşayabileceği güvenli bir ortam arayan Mia, Afrika’da zorlu bir maceraya atılır.\" rating=\"7.3\" actors=\"Daniah De Villiers, Mélanie Laurent, Langley Kirkwood, Ryan Mac Lennan, Lionel Newton\" director=\"Gilles de Maistre\"",
    "title": "Vahşi Dostum",
    "poster": "https://image.tmdb.org/t/p/w500/jT2eE40R4PWEJ7PGIV4xEeZSsFb.jpg",
    "overview": "On yaşındaki Mia’nın Londra’da mutlu bir hayatı vardır. Fakat bir aslan çiftliğini işletmek için ailesi Güney Afrika’ya taşınmaya karar verir. Mia, başlarda bu karardan dolayı oldukça mutsuzdur. Fakat bembeyaz bir aslan olan Charlie doğduğunda Mia’nın hayatı güzelleşmeye başlar. Mia ve Charlie’nin arasında mükemmel bir bağ oluşmuştur. Her şey yolunda giderken babasının sakladığı sırrın ortaya çıkması ailenin hayatını alt üst eder. Öğrendiklerinden sonra Charlie’nin zarar görebileceğini düşünen Mia, Charlie ile birlikte kaçar. Charlie’nin yaşayabileceği güvenli bir ortam arayan Mia, Afrika’da zorlu bir maceraya atılır.",
    "rating": "7.3",
    "actors": "Daniah De Villiers, Mélanie Laurent, Langley Kirkwood, Ryan Mac Lennan, Lionel Newton",
    "director": "Gilles de Maistre",
    "unsure": false
  },
  "Vahşiler Firarda||2016": {
    "extinf": "#EXTINF:-1 tvg-name=\"Vahşiler Firarda\" tvg-logo=\"https://image.tmdb.org/t/p/w500/hkmz9rxgcweizXNElozGeKwmAJE.jpg\" group-title=\"VOD\" title=\"Vahşiler Firarda\" desc=\"Ricky, koruyucu ailesiyle birlikte Yeni Zelanda kırsalında mutlu bir yaşam sürmektedir. Ancak üvey annesinin ani ölümünden sonra çocuk esirgeme kurumu onu geri almaya niyetlenir.  Hayatından vazgeçmeye hiç niyeti olmayan Ricky, üvey babasıyla birlikte ormanın derinliklerine doğru bir kaçış yolculuğuna koyulur..\" rating=\"7.653\" actors=\"Sam Neill, Julian Dennison, Rima Te Wiata, Rachel House, Tioreore Ngatai-Melbourne\" director=\"Taika Waititi\"",
    "title": "Vahşiler Firarda",
    "poster": "https://image.tmdb.org/t/p/w500/hkmz9rxgcweizXNElozGeKwmAJE.jpg",
    "overview": "Ricky, koruyucu ailesiyle birlikte Yeni Zelanda kırsalında mutlu bir yaşam sürmektedir. Ancak üvey annesinin ani ölümünden sonra çocuk esirgeme kurumu onu geri almaya niyetlenir.  Hayatından vazgeçmeye hiç niyeti olmayan Ricky, üvey babasıyla birlikte ormanın derinliklerine doğru bir kaçış yolculuğuna koyulur..",
    "rating": "7.653",
    "actors": "Sam Neill, Julian Dennison, Rima Te Wiata, Rachel House, Tioreore Ngatai-Melbourne",
    "director": "Taika Waititi",
    "unsure": false
  },
  "Valhalla||1986": {
    "extinf": "#EXTINF:-1 tvg-name=\"Valhalla\" tvg-logo=\"https://image.tmdb.org/t/p/w500/xxtRD332Pv55ZMVcGhecvnFXkRW.jpg\" group-title=\"VOD\" title=\"Valhalla\" rating=\"6.8\" actors=\"Dick Kaysø, Preben Kristensen, Laura Bro, Marie Ingerslev, Susse Wold\" director=\"Peter Madsen\"",
    "title": "Valhalla",
    "poster": "https://image.tmdb.org/t/p/w500/xxtRD332Pv55ZMVcGhecvnFXkRW.jpg",
    "overview": "",
    "rating": "6.8",
    "actors": "Dick Kaysø, Preben Kristensen, Laura Bro, Marie Ingerslev, Susse Wold",
    "director": "Peter Madsen",
    "unsure": false
  },
  "Valhalla||2019": {
    "extinf": "#EXTINF:-1 tvg-name=\"Valhalla\" tvg-logo=\"https://image.tmdb.org/t/p/w500/xNcbjsoGYI7la7ByLNjo2uMS7LS.jpg\" group-title=\"VOD\" title=\"Valhalla\" rating=\"5.261\" actors=\"Roland Møller, Patricia Schumann, Jacob Lohmann, Salome R. Gunnarsdottir, Dulfi Al-Jabouri\" director=\"Fenar Ahmad\"",
    "title": "Valhalla",
    "poster": "https://image.tmdb.org/t/p/w500/xNcbjsoGYI7la7ByLNjo2uMS7LS.jpg",
    "overview": "",
    "rating": "5.261",
    "actors": "Roland Møller, Patricia Schumann, Jacob Lohmann, Salome R. Gunnarsdottir, Dulfi Al-Jabouri",
    "director": "Fenar Ahmad",
    "unsure": false
  },
  "Vegas'ta Korku ve Nefret||1998": {
    "extinf": "#EXTINF:-1 tvg-name=\"Vegas'ta Korku ve Nefret\" tvg-logo=\"https://image.tmdb.org/t/p/w500/8VDD9hRYnwUhun6JTC8sKScTjOc.jpg\" group-title=\"VOD\" title=\"Vegas'ta Korku ve Nefret\" desc=\"Raoul Duke ve avukatı Dr. Gonzo, bir motosiklet yarışını izlemek için Mojave Çölü'nde bir bavul dolusu uyuşturucu ve kırmızı bir üstü açık arabayla Las Vegas'a giderler. Uyuşturucu tüketimleri endişe verici bir hızla artarken, uyuşturucu bağımlısı ikili otel odalarını mahveder ve yasal yaptırımlardan korkarlar. Duke, Los Angeles'a geri dönmek için yola çıkar, ancak bir polisle yaşadığı tuhaf olayın ardından Günah Şehri'ne geri döner ve çılgın uyuşturucu serüvenine devam eder.\" rating=\"7.211\" actors=\"Johnny Depp, Benicio del Toro, Tobey Maguire, Michael Lee Gogin, Larry Cedar\" director=\"Terry Gilliam\"",
    "title": "Vegas'ta Korku ve Nefret",
    "poster": "https://image.tmdb.org/t/p/w500/8VDD9hRYnwUhun6JTC8sKScTjOc.jpg",
    "overview": "Raoul Duke ve avukatı Dr. Gonzo, bir motosiklet yarışını izlemek için Mojave Çölü'nde bir bavul dolusu uyuşturucu ve kırmızı bir üstü açık arabayla Las Vegas'a giderler. Uyuşturucu tüketimleri endişe verici bir hızla artarken, uyuşturucu bağımlısı ikili otel odalarını mahveder ve yasal yaptırımlardan korkarlar. Duke, Los Angeles'a geri dönmek için yola çıkar, ancak bir polisle yaşadığı tuhaf olayın ardından Günah Şehri'ne geri döner ve çılgın uyuşturucu serüvenine devam eder.",
    "rating": "7.211",
    "actors": "Johnny Depp, Benicio del Toro, Tobey Maguire, Michael Lee Gogin, Larry Cedar",
    "director": "Terry Gilliam",
    "unsure": false
  },
  "Vicky'nin Gizemli Dostu||2021": {
    "extinf": "#EXTINF:-1 tvg-name=\"Vicky'nin Gizemli Dostu\" tvg-logo=\"https://image.tmdb.org/t/p/w500/v17kM8POZGKOSlbzrim0ll5tyjj.jpg\" group-title=\"VOD\" title=\"Vicky'nin Gizemli Dostu\" desc=\"Annesini kaybeden acılı bir kız ile babası Cantal'a yerleşir. Acaba özel bir hayvan bu küçük kızın iyileşmesine yardımcı olabilir mi? Gerçek bir öyküden esinlendi.\" rating=\"7.1\" actors=\"Vincent Elbaz, Shanna Keil, Marie Gillain, Eric Elmosnino, Tchéky Karyo\" director=\"Denis Imbert\"",
    "title": "Vicky'nin Gizemli Dostu",
    "poster": "https://image.tmdb.org/t/p/w500/v17kM8POZGKOSlbzrim0ll5tyjj.jpg",
    "overview": "Annesini kaybeden acılı bir kız ile babası Cantal'a yerleşir. Acaba özel bir hayvan bu küçük kızın iyileşmesine yardımcı olabilir mi? Gerçek bir öyküden esinlendi.",
    "rating": "7.1",
    "actors": "Vincent Elbaz, Shanna Keil, Marie Gillain, Eric Elmosnino, Tchéky Karyo",
    "director": "Denis Imbert",
    "unsure": false
  },
  "Victor ve Timsah Konağının Sırrı||2012": {
    "extinf": "#EXTINF:-1 tvg-name=\"Victor ve Timsah Konağının Sırrı\" tvg-logo=\"https://image.tmdb.org/t/p/w500/r6f9otddmZx4qBvlR386AA41ZNm.jpg\" group-title=\"VOD\" title=\"Victor ve Timsah Konağının Sırrı\" desc=\"11 yaşındaki Viktor ailesi ile birlikte ürkütücü bir konakta yaşamaktadır Yolculuğa çıkan anne-babası birkaç günlüğüne Viktor'u evde kızkardeşi ile birlikte yalnız bırakır Aynı günlerde Viktor evde timsaha benzeyen, içi doldurulmuş bir oyuncak ve ölmüş kuzenine ait eski bir günlük bulur Bu keşif onu akıl almaz bir maceraya sürükleyecektir.\" rating=\"6.3\" actors=\"Kristo Ferkic, Joanna Ferkic, Vijessna Ferkic, Christoph Maria Herbst, Gudrun Ritter\" director=\"Cyrill Boss\"",
    "title": "Victor ve Timsah Konağının Sırrı",
    "poster": "https://image.tmdb.org/t/p/w500/r6f9otddmZx4qBvlR386AA41ZNm.jpg",
    "overview": "11 yaşındaki Viktor ailesi ile birlikte ürkütücü bir konakta yaşamaktadır Yolculuğa çıkan anne-babası birkaç günlüğüne Viktor'u evde kızkardeşi ile birlikte yalnız bırakır Aynı günlerde Viktor evde timsaha benzeyen, içi doldurulmuş bir oyuncak ve ölmüş kuzenine ait eski bir günlük bulur Bu keşif onu akıl almaz bir maceraya sürükleyecektir.",
    "rating": "6.3",
    "actors": "Kristo Ferkic, Joanna Ferkic, Vijessna Ferkic, Christoph Maria Herbst, Gudrun Ritter",
    "director": "Cyrill Boss",
    "unsure": false
  }
}